dashjson.py
dashjson-0.1.5.dist-info/LICENSE.txt
dashjson-0.1.5.dist-info/METADATA
dashjson-0.1.5.dist-info/WHEEL
dashjson-0.1.5.dist-info/top_level.txt
dashjson-0.1.5.dist-info/RECORD
