Metadata-Version: 2.1
Name: dashjson
Version: 0.1.5
Summary: A tool for exporting (or importing) Datadog dashboards to (or from) json
Home-page: https://github.com/ouyi/dashjson
Author: Yi Ou
Author-email: dashjson.project@gmail.com
License: UNKNOWN
Platform: UNKNOWN
Classifier: Programming Language :: Python :: 3
Classifier: License :: OSI Approved :: MIT License
Classifier: Operating System :: OS Independent
Requires-Dist: datadog (>=0.26.0)
